{
    "isValid": false,
    "score": 100000000,
    "bonusObtained": [],
    "error": {
        "srcEdge": {
            "src": {
                "x": 168,
                "y": 11
            },
            "dst": {
                "x": 151,
                "y": 34
            }
        },
        "dstEdge": {
            "src": {
                "x": 362,
                "y": 162
            },
            "dst": {
                "x": 339,
                "y": 146
            }
        },
        "message": "Edge 7 violates the length constraint. (51 edges violates in total.)"
    }
}